<?xml version="1.0" encoding="UTF-8" ?>
<report><printSet pageFontName="宋体" pageFontSize="9" pageFontStyleBold="0" pageFontStyleItalic="0" pageFooterCenterText="" pageHeaderCenterText="" pageFooterLeftText="" pageHeaderLeftText="" pageFooterRightText="" pageHeaderRightText="" pageHeight="2970" pageWidth="2100" paperSize="9" PrintOrientation="1" paperSource="256" reportTop="2" bottomHeight="16" reportLeft="1" rightWidth="16" HeaderMargin="80" footerMargin="120" topMargin="200" bottomMargin="200" leftMargin="200" rightMargin="200"/><reportSection headStartRow="1" headRowCount="2" footStartRow="4" footRowCount="2" printType="0"/><detailSection startRow="3" rowCount="1" fixRow="0" reportType="0" columns="0" chartType="0" seriesNO="0"/><cell rowCount="5" colCount="6"><cols><col index="1" width="97"/><col index="2" width="94"/><col index="3" width="80"/><col index="4" width="111"/><col index="5" width="112"/><col index="6" width="146"/></cols><rows><row index="1" height="50"><col index="1" fontName="宋体" fontSize="20" bold="0" italic="0" underline="0" limitedLine="0" vertical="1" align="1" borderWidth1="0" borderWidth2="0" borderWidth3="0" borderWidth4="0" caption="家庭成员" field="" format="0" sumFun="0" sumGroup="" sumType="0" formula="" asRowNumber="0" picStretch="1" picUrl="" printHide="0" cellStatus="1" mergeCols="5" mergeRows="0" note="" direction="0" script="" linkReport="" showzero="0" chartAxis="0" seriesNO="0"/><col index="2" fontName="宋体" fontSize="20" bold="0" italic="0" underline="0" limitedLine="0" vertical="1" align="1" borderWidth1="0" borderWidth2="0" borderWidth3="0" borderWidth4="0" caption="" field="" format="0" sumFun="0" sumGroup="" sumType="0" formula="" asRowNumber="0" picStretch="0" picUrl="" printHide="0" cellStatus="2" mergeCols="0" mergeRows="0" note="" direction="0" script="" linkReport="" showzero="0" chartAxis="0" seriesNO="0"/><col index="3" fontName="宋体" fontSize="20" bold="0" italic="0" underline="0" limitedLine="0" vertical="1" align="1" borderWidth1="0" borderWidth2="0" borderWidth3="0" borderWidth4="0" caption="" field="" format="0" sumFun="0" sumGroup="" sumType="0" formula="" asRowNumber="0" picStretch="0" picUrl="" printHide="0" cellStatus="2" mergeCols="0" mergeRows="0" note="" direction="0" script="" linkReport="" showzero="0" chartAxis="0" seriesNO="0"/><col index="4" fontName="宋体" fontSize="20" bold="0" italic="0" underline="0" limitedLine="0" vertical="1" align="1" borderWidth1="0" borderWidth2="0" borderWidth3="0" borderWidth4="0" caption="" field="" format="0" sumFun="0" sumGroup="" sumType="0" formula="" asRowNumber="0" picStretch="0" picUrl="" printHide="0" cellStatus="2" mergeCols="0" mergeRows="0" note="" direction="0" script="" linkReport="" showzero="0" chartAxis="0" seriesNO="0"/><col index="5" fontName="宋体" fontSize="20" bold="0" italic="0" underline="0" limitedLine="0" vertical="1" align="1" borderWidth1="0" borderWidth2="0" borderWidth3="0" borderWidth4="0" caption="" field="" format="0" sumFun="0" sumGroup="" sumType="0" formula="" asRowNumber="0" picStretch="0" picUrl="" printHide="0" cellStatus="2" mergeCols="0" mergeRows="0" note="" direction="0" script="" linkReport="" showzero="0" chartAxis="0" seriesNO="0"/><col index="6" fontName="宋体" fontSize="20" bold="0" italic="0" underline="0" limitedLine="0" vertical="1" align="1" borderWidth1="0" borderWidth2="0" borderWidth3="0" borderWidth4="0" caption="" field="" format="0" sumFun="0" sumGroup="" sumType="0" formula="" asRowNumber="0" picStretch="0" picUrl="" printHide="0" cellStatus="2" mergeCols="0" mergeRows="0" note="" direction="0" script="" linkReport="" showzero="0" chartAxis="0" seriesNO="0"/></row><row index="2" height="19"><col index="1" fontName="宋体" fontSize="10" bold="0" italic="0" underline="0" limitedLine="0" vertical="1" align="1" borderWidth1="2" borderWidth2="2" borderWidth3="1" borderWidth4="1" caption="家庭成员姓名" field="" format="0" sumFun="0" sumGroup="" sumType="0" formula="" asRowNumber="0" picStretch="0" picUrl="" printHide="0" cellStatus="0" mergeCols="0" mergeRows="0" note="" direction="0" script="" linkReport="" showzero="0" chartAxis="0" seriesNO="0"/><col index="2" fontName="宋体" fontSize="10" bold="0" italic="0" underline="0" limitedLine="0" vertical="1" align="1" borderWidth1="1" borderWidth2="2" borderWidth3="1" borderWidth4="1" caption="关系" field="" format="0" sumFun="0" sumGroup="" sumType="0" formula="" asRowNumber="0" picStretch="0" picUrl="" printHide="0" cellStatus="0" mergeCols="0" mergeRows="0" note="" direction="0" script="" linkReport="" showzero="0" chartAxis="0" seriesNO="0"/><col index="3" fontName="宋体" fontSize="10" bold="0" italic="0" underline="0" limitedLine="0" vertical="1" align="1" borderWidth1="1" borderWidth2="2" borderWidth3="1" borderWidth4="1" caption="政治面貌" field="" format="0" sumFun="0" sumGroup="" sumType="0" formula="" asRowNumber="0" picStretch="0" picUrl="" printHide="0" cellStatus="0" mergeCols="0" mergeRows="0" note="" direction="0" script="" linkReport="" showzero="0" chartAxis="0" seriesNO="0"/><col index="4" fontName="宋体" fontSize="10" bold="0" italic="0" underline="0" limitedLine="0" vertical="1" align="1" borderWidth1="1" borderWidth2="2" borderWidth3="1" borderWidth4="1" caption="家庭电话" field="" format="0" sumFun="0" sumGroup="" sumType="0" formula="" asRowNumber="0" picStretch="0" picUrl="" printHide="0" cellStatus="0" mergeCols="0" mergeRows="0" note="" direction="0" script="" linkReport="" showzero="0" chartAxis="0" seriesNO="0"/><col index="5" fontName="宋体" fontSize="10" bold="0" italic="0" underline="0" limitedLine="0" vertical="1" align="1" borderWidth1="1" borderWidth2="2" borderWidth3="1" borderWidth4="1" caption="移动电话" field="" format="0" sumFun="0" sumGroup="" sumType="0" formula="" asRowNumber="0" picStretch="0" picUrl="" printHide="0" cellStatus="0" mergeCols="0" mergeRows="0" note="" direction="0" script="" linkReport="" showzero="0" chartAxis="0" seriesNO="0"/><col index="6" fontName="宋体" fontSize="10" bold="0" italic="0" underline="0" limitedLine="0" vertical="1" align="1" borderWidth1="1" borderWidth2="2" borderWidth3="2" borderWidth4="1" caption="工作单位" field="" format="0" sumFun="0" sumGroup="" sumType="0" formula="" asRowNumber="0" picStretch="0" picUrl="" printHide="0" cellStatus="0" mergeCols="0" mergeRows="0" note="" direction="0" script="" linkReport="" showzero="0" chartAxis="0" seriesNO="0"/></row><row index="3" height="19"><col index="1" fontName="宋体" fontSize="10" bold="0" italic="0" underline="0" limitedLine="0" vertical="1" align="1" borderWidth1="2" borderWidth2="1" borderWidth3="1" borderWidth4="1" caption="" field="FamilyName" format="0" sumFun="0" sumGroup="" sumType="0" formula="" asRowNumber="0" picStretch="0" picUrl="" printHide="0" cellStatus="0" mergeCols="0" mergeRows="0" note="家庭成员姓名[FamilyName]" direction="0" script="" linkReport="" showzero="0" chartAxis="0" seriesNO="0"/><col index="2" fontName="宋体" fontSize="10" bold="0" italic="0" underline="0" limitedLine="0" vertical="1" align="1" borderWidth1="1" borderWidth2="1" borderWidth3="1" borderWidth4="1" caption="" field="Relation" format="0" sumFun="0" sumGroup="" sumType="0" formula="" asRowNumber="0" picStretch="1" picUrl="" printHide="0" cellStatus="0" mergeCols="0" mergeRows="0" note="关系[Relation]" direction="0" script="" linkReport="" showzero="0" chartAxis="0" seriesNO="0"/><col index="3" fontName="宋体" fontSize="10" bold="0" italic="0" underline="0" limitedLine="0" vertical="1" align="1" borderWidth1="1" borderWidth2="1" borderWidth3="1" borderWidth4="1" caption="" field="Politics" format="0" sumFun="0" sumGroup="" sumType="0" formula="" asRowNumber="0" picStretch="0" picUrl="" printHide="0" cellStatus="0" mergeCols="0" mergeRows="0" note="政治面貌[Politics]" direction="0" script="" linkReport="" showzero="0" chartAxis="0" seriesNO="0"/><col index="4" fontName="宋体" fontSize="10" bold="0" italic="0" underline="0" limitedLine="0" vertical="1" align="1" borderWidth1="1" borderWidth2="1" borderWidth3="1" borderWidth4="1" caption="" field="HomePhone" format="0" sumFun="0" sumGroup="" sumType="0" formula="" asRowNumber="0" picStretch="0" picUrl="" printHide="0" cellStatus="0" mergeCols="0" mergeRows="0" note="家庭电话[HomePhone]" direction="0" script="" linkReport="" showzero="0" chartAxis="0" seriesNO="0"/><col index="5" fontName="宋体" fontSize="10" bold="0" italic="0" underline="0" limitedLine="0" vertical="1" align="1" borderWidth1="1" borderWidth2="1" borderWidth3="1" borderWidth4="1" caption="" field="Mobiletelephone" format="0" sumFun="0" sumGroup="" sumType="0" formula="" asRowNumber="0" picStretch="0" picUrl="" printHide="0" cellStatus="0" mergeCols="0" mergeRows="0" note="移动电话[Mobiletelephone]" direction="0" script="" linkReport="" showzero="0" chartAxis="0" seriesNO="0"/><col index="6" fontName="宋体" fontSize="10" bold="0" italic="0" underline="0" limitedLine="0" vertical="1" align="1" borderWidth1="1" borderWidth2="1" borderWidth3="2" borderWidth4="1" caption="" field="Unit" format="0" sumFun="0" sumGroup="" sumType="0" formula="" asRowNumber="0" picStretch="0" picUrl="" printHide="0" cellStatus="0" mergeCols="0" mergeRows="0" note="工作单位[Unit]" direction="0" script="" linkReport="" showzero="0" chartAxis="0" seriesNO="0"/></row><row index="4" height="1"><col index="1" fontName="宋体" fontSize="12" bold="0" italic="0" underline="0" limitedLine="0" vertical="1" align="0" borderWidth1="2" borderWidth2="1" borderWidth3="1" borderWidth4="2" caption="" field="" format="0" sumFun="0" sumGroup="" sumType="0" formula="" asRowNumber="0" picStretch="0" picUrl="" printHide="0" cellStatus="0" mergeCols="0" mergeRows="0" note="" direction="0" script="" linkReport="" showzero="0" chartAxis="0" seriesNO="0"/><col index="2" fontName="宋体" fontSize="12" bold="0" italic="0" underline="0" limitedLine="0" vertical="1" align="0" borderWidth1="1" borderWidth2="1" borderWidth3="1" borderWidth4="2" caption="" field="" format="0" sumFun="0" sumGroup="" sumType="0" formula="" asRowNumber="0" picStretch="0" picUrl="" printHide="0" cellStatus="0" mergeCols="0" mergeRows="0" note="" direction="0" script="" linkReport="" showzero="0" chartAxis="0" seriesNO="0"/><col index="3" fontName="宋体" fontSize="12" bold="0" italic="0" underline="0" limitedLine="0" vertical="1" align="0" borderWidth1="1" borderWidth2="1" borderWidth3="1" borderWidth4="2" caption="" field="" format="0" sumFun="0" sumGroup="" sumType="0" formula="" asRowNumber="0" picStretch="0" picUrl="" printHide="0" cellStatus="0" mergeCols="0" mergeRows="0" note="" direction="0" script="" linkReport="" showzero="0" chartAxis="0" seriesNO="0"/><col index="4" fontName="宋体" fontSize="12" bold="0" italic="0" underline="0" limitedLine="0" vertical="1" align="0" borderWidth1="1" borderWidth2="1" borderWidth3="1" borderWidth4="2" caption="" field="" format="0" sumFun="0" sumGroup="" sumType="0" formula="" asRowNumber="0" picStretch="0" picUrl="" printHide="0" cellStatus="0" mergeCols="0" mergeRows="0" note="" direction="0" script="" linkReport="" showzero="0" chartAxis="0" seriesNO="0"/><col index="5" fontName="宋体" fontSize="12" bold="0" italic="0" underline="0" limitedLine="0" vertical="1" align="0" borderWidth1="1" borderWidth2="1" borderWidth3="1" borderWidth4="2" caption="" field="" format="0" sumFun="0" sumGroup="" sumType="0" formula="" asRowNumber="0" picStretch="0" picUrl="" printHide="0" cellStatus="0" mergeCols="0" mergeRows="0" note="" direction="0" script="" linkReport="" showzero="0" chartAxis="0" seriesNO="0"/><col index="6" fontName="宋体" fontSize="12" bold="0" italic="0" underline="0" limitedLine="0" vertical="1" align="0" borderWidth1="1" borderWidth2="1" borderWidth3="2" borderWidth4="2" caption="" field="" format="0" sumFun="0" sumGroup="" sumType="0" formula="" asRowNumber="0" picStretch="0" picUrl="" printHide="0" cellStatus="0" mergeCols="0" mergeRows="0" note="" direction="0" script="" linkReport="" showzero="0" chartAxis="0" seriesNO="0"/></row><row index="5" height="19"><col index="1" fontName="宋体" fontSize="12" bold="0" italic="0" underline="0" limitedLine="0" vertical="1" align="0" borderWidth1="0" borderWidth2="0" borderWidth3="0" borderWidth4="0" caption="" field="" format="0" sumFun="0" sumGroup="" sumType="0" formula="" asRowNumber="0" picStretch="0" picUrl="" printHide="0" cellStatus="0" mergeCols="0" mergeRows="0" note="" direction="0" script="" linkReport="" showzero="0" chartAxis="0" seriesNO="0"/><col index="2" fontName="宋体" fontSize="12" bold="0" italic="0" underline="0" limitedLine="0" vertical="1" align="0" borderWidth1="0" borderWidth2="0" borderWidth3="0" borderWidth4="0" caption="" field="" format="0" sumFun="0" sumGroup="" sumType="0" formula="" asRowNumber="0" picStretch="0" picUrl="" printHide="0" cellStatus="0" mergeCols="0" mergeRows="0" note="" direction="0" script="" linkReport="" showzero="0" chartAxis="0" seriesNO="0"/><col index="3" fontName="宋体" fontSize="12" bold="0" italic="0" underline="0" limitedLine="0" vertical="1" align="0" borderWidth1="0" borderWidth2="0" borderWidth3="0" borderWidth4="0" caption="" field="" format="0" sumFun="0" sumGroup="" sumType="0" formula="" asRowNumber="0" picStretch="0" picUrl="" printHide="0" cellStatus="0" mergeCols="0" mergeRows="0" note="" direction="0" script="" linkReport="" showzero="0" chartAxis="0" seriesNO="0"/><col index="4" fontName="宋体" fontSize="12" bold="0" italic="0" underline="0" limitedLine="0" vertical="1" align="0" borderWidth1="0" borderWidth2="0" borderWidth3="0" borderWidth4="0" caption="" field="" format="0" sumFun="0" sumGroup="" sumType="0" formula="" asRowNumber="0" picStretch="0" picUrl="" printHide="0" cellStatus="0" mergeCols="0" mergeRows="0" note="" direction="0" script="" linkReport="" showzero="0" chartAxis="0" seriesNO="0"/><col index="5" fontName="宋体" fontSize="12" bold="0" italic="0" underline="0" limitedLine="0" vertical="1" align="0" borderWidth1="0" borderWidth2="0" borderWidth3="0" borderWidth4="0" caption="" field="" format="0" sumFun="0" sumGroup="" sumType="0" formula="" asRowNumber="0" picStretch="0" picUrl="" printHide="0" cellStatus="0" mergeCols="0" mergeRows="0" note="" direction="0" script="" linkReport="" showzero="0" chartAxis="0" seriesNO="0"/><col index="6" fontName="宋体" fontSize="12" bold="0" italic="0" underline="0" limitedLine="0" vertical="1" align="0" borderWidth1="0" borderWidth2="0" borderWidth3="0" borderWidth4="0" caption="" field="" format="0" sumFun="0" sumGroup="" sumType="0" formula="" asRowNumber="0" picStretch="0" picUrl="" printHide="0" cellStatus="0" mergeCols="0" mergeRows="0" note="" direction="0" script="" linkReport="" showzero="0" chartAxis="0" seriesNO="0"/></row></rows></cell><appendData><![CDATA[REPORTX2.6.0.0#eJytlFtrE1EQx2c2mzaJtU2bqq31Em/1vm629fYgWHWLL+pSFFqCgbUuuJCbGBEfDIL4BfINBPvs--jQqlQpGCIGqVYtUvoL7l1QfBePbkTLLE1KSbbDiTvcx//jPnl+yEblyauDwZ7tSUY4qqqFEAnEYA--6GDLL7FwkK1eH8jhsdGoFlOjj15HtZPHo6mU388uFdXPrhS1AzoBA74TiirHNEUNyhp7VBNCuA67--WLX1bEE31Bw9cD2M0It9EKl91I8bcCNdbMIBHMTN7CzsrCEWglsAtsI2+d3S++/QtR0MiDhzwA6A--nQC7AHYD7AEYBtgLsA9gPxxgc5VKpUMAh1mepAAcQbWsDwqf9lzFqG3NCSNsZ0edk5LKwkMEExKs--2wxkoSD2HHDMCXiGRQnPsujDc05Z1B0iOC6xUhH2Qb5Pfi6JcYnGJSNcMsolR31uB7mq5DJuVzrN--Qhqrmy3dd7r1sRB4tfxh5sXbz89k1+Oyo788Zb+4F0QcCPMzVMuh8h2rvY0qt7SpptO1yVbEsewi--y08ri7+FSahqEpIk5LrV3NRV3O6Rm05u9Yqjq3ho3EzZybsXzZTVlM0QDLh7j1flV3kH49TBpOiA--+0lehjlFpaZomLVWGEahdI6EA0GW/kXKU01K1UQq5yTPffs4W2cL0SOfm+Sik0u94m4+gQkraebs--TLqpn9wQdDsdx0nkYmIKJgnOBFthYgomCc9MFsS4xn+ZWJSqiVTOJLDy58vS4o/F523kcpucdHJq--yMXIJO2cPX2ryX9NH3UdJ6GLzYJgY7TOZkGwMbyywR4xcqYhG56qidRI5VU6+3P+aRvZ3CEnnZwa--sQmez6Qs40Ym3ewrLUJtxyvKKh3uPSm8W6PDS03RGJ7o5MXQ2cZ08oJOtkJn+c3LJ22m84CcdHJq--RKfnQuaanbRyVtLKroHRIDUfr9G7SOUFqWzrpPKCVNYzqaLYgEJjUkVBqlAhNff466/ZmaX5uqQk--T6RS5KSTU11SruLylbSdaxJPN3Ucd0QuJkXBpCCYSN6ZFAWTwlqZlP4C28h90g==#]]></appendData></report>
