<?xml version="1.0" encoding="UTF-8" ?>
<report><printSet pageFontName="宋体" pageFontSize="9" pageFontStyleBold="0" pageFontStyleItalic="0" pageFooterCenterText="" pageHeaderCenterText="" pageFooterLeftText="" pageHeaderLeftText="" pageFooterRightText="" pageHeaderRightText="" pageHeight="2970" pageWidth="2100" paperSize="9" PrintOrientation="1" paperSource="256" reportTop="2" bottomHeight="16" reportLeft="1" rightWidth="16" HeaderMargin="80" footerMargin="120" topMargin="200" bottomMargin="200" leftMargin="200" rightMargin="200"/><reportSection headStartRow="1" headRowCount="2" footStartRow="4" footRowCount="2" printType="0"/><detailSection startRow="3" rowCount="1" fixRow="0" reportType="0" columns="0" chartType="0" seriesNO="0"/><cell rowCount="5" colCount="4"><cols><col index="1" width="180"/><col index="2" width="103"/><col index="3" width="159"/><col index="4" width="107"/></cols><rows><row index="1" height="56"><col index="1" fontName="宋体" fontSize="15" bold="1" italic="0" underline="0" limitedLine="0" vertical="1" align="1" borderWidth1="0" borderWidth2="0" borderWidth3="0" borderWidth4="0" caption="序列号详情" field="" format="0" sumFun="0" sumGroup="" sumType="0" formula="" asRowNumber="0" picStretch="1" picUrl="" printHide="0" cellStatus="1" mergeCols="3" mergeRows="0" note="" direction="0" script="" linkReport="" showzero="0" chartAxis="0" seriesNO="0"/><col index="2" fontName="宋体" fontSize="15" bold="1" italic="0" underline="0" limitedLine="0" vertical="1" align="1" borderWidth1="0" borderWidth2="0" borderWidth3="0" borderWidth4="0" caption="" field="" format="0" sumFun="0" sumGroup="" sumType="0" formula="" asRowNumber="0" picStretch="0" picUrl="" printHide="0" cellStatus="2" mergeCols="0" mergeRows="0" note="" direction="0" script="" linkReport="" showzero="0" chartAxis="0" seriesNO="0"/><col index="3" fontName="宋体" fontSize="15" bold="1" italic="0" underline="0" limitedLine="0" vertical="1" align="1" borderWidth1="0" borderWidth2="0" borderWidth3="0" borderWidth4="0" caption="" field="" format="0" sumFun="0" sumGroup="" sumType="0" formula="" asRowNumber="0" picStretch="0" picUrl="" printHide="0" cellStatus="2" mergeCols="0" mergeRows="0" note="" direction="0" script="" linkReport="" showzero="0" chartAxis="0" seriesNO="0"/><col index="4" fontName="宋体" fontSize="15" bold="1" italic="0" underline="0" limitedLine="0" vertical="1" align="1" borderWidth1="0" borderWidth2="0" borderWidth3="0" borderWidth4="0" caption="" field="" format="0" sumFun="0" sumGroup="" sumType="0" formula="" asRowNumber="0" picStretch="0" picUrl="" printHide="0" cellStatus="2" mergeCols="0" mergeRows="0" note="" direction="0" script="" linkReport="" showzero="0" chartAxis="0" seriesNO="0"/></row><row index="2" height="19"><col index="1" fontName="宋体" fontSize="12" bold="0" italic="0" underline="0" limitedLine="0" vertical="1" align="1" borderWidth1="2" borderWidth2="2" borderWidth3="1" borderWidth4="1" caption="序列号" field="" format="0" sumFun="0" sumGroup="" sumType="0" formula="" asRowNumber="0" picStretch="1" picUrl="" printHide="0" cellStatus="0" mergeCols="0" mergeRows="0" note="" direction="0" script="" linkReport="" showzero="0" chartAxis="0" seriesNO="0"/><col index="2" fontName="宋体" fontSize="12" bold="0" italic="0" underline="0" limitedLine="0" vertical="1" align="1" borderWidth1="1" borderWidth2="2" borderWidth3="1" borderWidth4="1" caption="商品编号" field="" format="0" sumFun="0" sumGroup="" sumType="0" formula="" asRowNumber="0" picStretch="1" picUrl="" printHide="0" cellStatus="0" mergeCols="0" mergeRows="0" note="" direction="0" script="" linkReport="" showzero="0" chartAxis="0" seriesNO="0"/><col index="3" fontName="宋体" fontSize="12" bold="0" italic="0" underline="0" limitedLine="0" vertical="1" align="1" borderWidth1="1" borderWidth2="2" borderWidth3="1" borderWidth4="1" caption="商品名称" field="" format="0" sumFun="0" sumGroup="" sumType="0" formula="" asRowNumber="0" picStretch="1" picUrl="" printHide="0" cellStatus="0" mergeCols="0" mergeRows="0" note="" direction="0" script="" linkReport="" showzero="0" chartAxis="0" seriesNO="0"/><col index="4" fontName="宋体" fontSize="12" bold="0" italic="0" underline="0" limitedLine="0" vertical="1" align="1" borderWidth1="1" borderWidth2="2" borderWidth3="2" borderWidth4="1" caption="商品规格" field="" format="0" sumFun="0" sumGroup="" sumType="0" formula="" asRowNumber="0" picStretch="1" picUrl="" printHide="0" cellStatus="0" mergeCols="0" mergeRows="0" note="" direction="0" script="" linkReport="" showzero="0" chartAxis="0" seriesNO="0"/></row><row index="3" height="21"><col index="1" fontName="宋体" fontSize="12" bold="0" italic="0" underline="0" limitedLine="0" vertical="1" align="0" borderWidth1="2" borderWidth2="1" borderWidth3="1" borderWidth4="2" caption="" field="Seq" format="0" sumFun="0" sumGroup="" sumType="0" formula="" asRowNumber="0" picStretch="1" picUrl="" printHide="0" cellStatus="0" mergeCols="0" mergeRows="0" note="序列号[Seq]" direction="0" script="" linkReport="" showzero="0" chartAxis="0" seriesNO="0"/><col index="2" fontName="宋体" fontSize="12" bold="0" italic="0" underline="0" limitedLine="0" vertical="1" align="0" borderWidth1="1" borderWidth2="1" borderWidth3="1" borderWidth4="2" caption="" field="GoodsNumber" format="0" sumFun="0" sumGroup="" sumType="0" formula="" asRowNumber="0" picStretch="1" picUrl="" printHide="0" cellStatus="0" mergeCols="0" mergeRows="0" note="商品编号[GoodsNumber]" direction="0" script="" linkReport="" showzero="0" chartAxis="0" seriesNO="0"/><col index="3" fontName="宋体" fontSize="12" bold="0" italic="0" underline="0" limitedLine="0" vertical="1" align="0" borderWidth1="1" borderWidth2="1" borderWidth3="1" borderWidth4="2" caption="" field="GoodsFullName" format="0" sumFun="0" sumGroup="" sumType="0" formula="" asRowNumber="0" picStretch="0" picUrl="" printHide="0" cellStatus="0" mergeCols="0" mergeRows="0" note="商品名称[GoodsFullName]" direction="0" script="" linkReport="" showzero="0" chartAxis="0" seriesNO="0"/><col index="4" fontName="宋体" fontSize="12" bold="0" italic="0" underline="0" limitedLine="0" vertical="1" align="0" borderWidth1="1" borderWidth2="1" borderWidth3="2" borderWidth4="2" caption="" field="GoodsSpec" format="0" sumFun="0" sumGroup="" sumType="0" formula="" asRowNumber="0" picStretch="0" picUrl="" printHide="0" cellStatus="0" mergeCols="0" mergeRows="0" note="商品规格[GoodsSpec]" direction="0" script="" linkReport="" showzero="0" chartAxis="0" seriesNO="0"/></row><row index="4" height="19"><col index="1" fontName="宋体" fontSize="12" bold="0" italic="0" underline="0" limitedLine="0" vertical="1" align="0" borderWidth1="0" borderWidth2="0" borderWidth3="0" borderWidth4="0" caption="" field="" format="0" sumFun="0" sumGroup="" sumType="0" formula="" asRowNumber="0" picStretch="0" picUrl="" printHide="0" cellStatus="0" mergeCols="0" mergeRows="0" note="" direction="0" script="" linkReport="" showzero="0" chartAxis="0" seriesNO="0"/><col index="2" fontName="宋体" fontSize="12" bold="0" italic="0" underline="0" limitedLine="0" vertical="1" align="0" borderWidth1="0" borderWidth2="0" borderWidth3="0" borderWidth4="0" caption="" field="" format="0" sumFun="0" sumGroup="" sumType="0" formula="" asRowNumber="0" picStretch="0" picUrl="" printHide="0" cellStatus="0" mergeCols="0" mergeRows="0" note="" direction="0" script="" linkReport="" showzero="0" chartAxis="0" seriesNO="0"/><col index="3" fontName="宋体" fontSize="12" bold="0" italic="0" underline="0" limitedLine="0" vertical="1" align="0" borderWidth1="0" borderWidth2="0" borderWidth3="0" borderWidth4="0" caption="" field="" format="0" sumFun="0" sumGroup="" sumType="0" formula="" asRowNumber="0" picStretch="0" picUrl="" printHide="0" cellStatus="0" mergeCols="0" mergeRows="0" note="" direction="0" script="" linkReport="" showzero="0" chartAxis="0" seriesNO="0"/><col index="4" fontName="宋体" fontSize="12" bold="0" italic="0" underline="0" limitedLine="0" vertical="1" align="0" borderWidth1="0" borderWidth2="0" borderWidth3="0" borderWidth4="0" caption="" field="" format="0" sumFun="0" sumGroup="" sumType="0" formula="" asRowNumber="0" picStretch="0" picUrl="" printHide="0" cellStatus="0" mergeCols="0" mergeRows="0" note="" direction="0" script="" linkReport="" showzero="0" chartAxis="0" seriesNO="0"/></row><row index="5" height="19"><col index="1" fontName="宋体" fontSize="12" bold="0" italic="0" underline="0" limitedLine="0" vertical="1" align="0" borderWidth1="0" borderWidth2="0" borderWidth3="0" borderWidth4="0" caption="" field="" format="0" sumFun="0" sumGroup="" sumType="0" formula="" asRowNumber="0" picStretch="0" picUrl="" printHide="0" cellStatus="0" mergeCols="0" mergeRows="0" note="" direction="0" script="" linkReport="" showzero="0" chartAxis="0" seriesNO="0"/><col index="2" fontName="宋体" fontSize="12" bold="0" italic="0" underline="0" limitedLine="0" vertical="1" align="0" borderWidth1="0" borderWidth2="0" borderWidth3="0" borderWidth4="0" caption="" field="" format="0" sumFun="0" sumGroup="" sumType="0" formula="" asRowNumber="0" picStretch="0" picUrl="" printHide="0" cellStatus="0" mergeCols="0" mergeRows="0" note="" direction="0" script="" linkReport="" showzero="0" chartAxis="0" seriesNO="0"/><col index="3" fontName="宋体" fontSize="12" bold="0" italic="0" underline="0" limitedLine="0" vertical="1" align="0" borderWidth1="0" borderWidth2="0" borderWidth3="0" borderWidth4="0" caption="" field="" format="0" sumFun="0" sumGroup="" sumType="0" formula="" asRowNumber="0" picStretch="0" picUrl="" printHide="0" cellStatus="0" mergeCols="0" mergeRows="0" note="" direction="0" script="" linkReport="" showzero="0" chartAxis="0" seriesNO="0"/><col index="4" fontName="宋体" fontSize="12" bold="0" italic="0" underline="0" limitedLine="0" vertical="1" align="0" borderWidth1="0" borderWidth2="0" borderWidth3="0" borderWidth4="0" caption="" field="" format="0" sumFun="0" sumGroup="" sumType="0" formula="" asRowNumber="0" picStretch="0" picUrl="" printHide="0" cellStatus="0" mergeCols="0" mergeRows="0" note="" direction="0" script="" linkReport="" showzero="0" chartAxis="0" seriesNO="0"/></row></rows></cell><appendData><![CDATA[REPORTX2.6.0.0#eJytkVtPE0EUx/9nL4W2IMVaQeul3u/rdkFdH0xEUR+aIAJRk8YEhaYxpQFs+DzEj2BsovaNGDFG--onwEXzTRN331oZ6ZnWlLkyZl7SbndKcz5zdnz2/mzvT9mbnHiT7Pueq4jpsBaIEAWBy2wekCx7AJ--KzExnvGybublRsa7fi1TLts2Lx3X5pXjRtAH6jd9x7WynuNGLY+32lKM4jTAtEEO7EHbM4TFBGGY--9iLZvrWPUrRfL0ZolA7QQX5LiEhzih4CDuOI9fnL1ncMHMU0kuI7cAw4DpwATgKngNPAGeAscA7n--+bvq9fpF4BKfMxzgMrlBfVTd05tVVrftiTTGkx0XL3WX0yqhiiLWUVLzBk2IRLc4G3Sbs0mTBnye--SIpDzMWWx7LymCePjcljgmrRFVMTrWaVLInIW29yWqHmYA2eCnyTU2z7z8Z27cPXXx9/Wi0HIPZg--B980JG4V4yYaTchdcoPU+M22/02uvHROM32OKkdSgCPBpcyLGQbJI7sFP9LgnAKnYkwyGihztrDa--FS2NeNBNniueSPYNzZ7XTXfqzu3QXYNQCUt4QKpSPEUxQMvoXkcn6kNN9RVV6uj/tLX55tW3QAiF--FPJco3MKnYpRq5D4veXlxcrUWvlZ4UWXYlK6r3xLbYuiqlJUDK2oqhSFIghFlFaK1nupSFJ9RW0q--ev/39eb/KCprdE6h2xQNyjHfXVtamnpaLnTVchojurP8juqmJnnjvP6YMJokoRKWIDXVlKZSTzXV--lKbSDk3vfrz9HWgyQmkqaHROoYUmo6kpKgc9u1JY6FJRUneVb1S26KkpPaXQempKz64J9X+6ff98--#]]></appendData></report>
